jrpysql/__init__.py
jrpysql/__version__.py
jrpysql/data/people.csv
jrpysql/data.py
jrpysql/database.py
jrpysql/vignettes/practical1.pdf
jrpysql/vignettes/solutions1.pdf
jrpysql/vignettes.py
jrpysql-0.1.5.dist-info/METADATA
jrpysql-0.1.5.dist-info/WHEEL
jrpysql-0.1.5.dist-info/RECORD
