Metadata-Version: 2.3
Name: jrpysql
Version: 0.1.5
Summary: Jumping Rivers: Introduction to SQL with Python
Author: Jumping Rivers
Author-email: info@jumpingrivers.com
Requires-Python: >=3.10
Classifier: Programming Language :: Python :: 3
Classifier: Programming Language :: Python :: 3.10
Classifier: Programming Language :: Python :: 3.11
Classifier: Programming Language :: Python :: 3.12
Classifier: Programming Language :: Python :: 3.13
Requires-Dist: jrpyintroduction (>=0.3.2,<0.4.0)
Requires-Dist: nycflights13 (>=0.0.3,<0.0.4)
Requires-Dist: pandas (>=1.4,<2.0)
Requires-Dist: psycopg2-binary (>=2.9.6,<3.0.0)
Requires-Dist: seaborn (>=0.12.2,<0.13.0)
Requires-Dist: sqlalchemy (>=2.0.12,<3.0.0)
